[
  {
    "notes": "",
    "first_name": "",
    "id": null,
    "company": "",
    "title": "",
    "byear": "",
    "work_number": "",
    "address_2": "",
    "phone2": "",
    "mobile_number": "",
    "ayear": "",
    "fax": "",
    "address": "",
    "py/object": "model.contact.Contact",
    "last_name": "",
    "email2": "",
    "home_number": "",
    "nickname": "",
    "email3": "",
    "all_emails_from_home_page": null,
    "all_phones_from_home_page": null,
    "email": "",
    "homepage": "",
    "middle_name": ""
  },
  {
    "notes": "notes\"oRF \"|*>",
    "first_name": "first_name|?",
    "id": null,
    "company": "companyea+Gmf^",
    "title": "titleEj<",
    "byear": "byear:",
    "work_number": "work_number!l&i",
    "address_2": "address_2fV!",
    "phone2": "phone2- >c)@",
    "mobile_number": "mobile_number#]",
    "ayear": "ayear",
    "fax": "faxogj[2 fb.",
    "address": "addressX4K{.Ih",
    "py/object": "model.contact.Contact",
    "last_name": "last_name",
    "email2": "email2)]",
    "home_number": "home_number;%",
    "nickname": "nickname^`@#dpk#J",
    "email3": "email3 ^\"TjF",
    "all_emails_from_home_page": null,
    "all_phones_from_home_page": null,
    "email": "emailGIc%qG",
    "homepage": "homepage< i",
    "middle_name": "middle_name@P"
  },
  {
    "notes": "notes0E",
    "first_name": "first_name\\6Jn qrV5",
    "id": null,
    "company": "companyh/48 L3T",
    "title": "title",
    "byear": "byearyuy@s",
    "work_number": "work_numbers[  L/8",
    "address_2": "address_2X",
    "phone2": "phone2Y4",
    "mobile_number": "mobile_number4{p}",
    "ayear": "ayearpn",
    "fax": "faxsR",
    "address": "addressn LlV\\!w",
    "py/object": "model.contact.Contact",
    "last_name": "last_name ;$.& {4A",
    "email2": "email2+ osIKO[o",
    "home_number": "home_number1C  '580",
    "nickname": "nicknameu82",
    "email3": "email3HVq/v-pcf",
    "all_emails_from_home_page": null,
    "all_phones_from_home_page": null,
    "email": "email/u g_",
    "homepage": "homepageLR %",
    "middle_name": "middle_nameRS\\>1!"
  },
  {
    "notes": "notes",
    "first_name": "first_name<'",
    "id": null,
    "company": "companyO",
    "title": "title",
    "byear": "byear SU~h  E",
    "work_number": "work_number F \"",
    "address_2": "address_2|I^0>",
    "phone2": "phone2>",
    "mobile_number": "mobile_number.I6Q@i|H",
    "ayear": "ayear~ q) ",
    "fax": "fax",
    "address": "address Sdtnz; `",
    "py/object": "model.contact.Contact",
    "last_name": "last_name]W",
    "email2": "email2|I#",
    "home_number": "home_number,R/O Q",
    "nickname": "nicknameV |oRP",
    "email3": "email3&nT",
    "all_emails_from_home_page": null,
    "all_phones_from_home_page": null,
    "email": "emailDI~#6/-",
    "homepage": "homepage& |",
    "middle_name": "middle_nameX*s\"m"
  },
  {
    "notes": "notesw'k1",
    "first_name": "first_name}",
    "id": null,
    "company": "company= c=]| Dq",
    "title": "titleAwI Q1",
    "byear": "byearc|V|Z[N5",
    "work_number": "work_numberS rlf",
    "address_2": "address_2j*l/F}P",
    "phone2": "phone2v'Kk",
    "mobile_number": "mobile_number% Q",
    "ayear": "ayearrg?i7}v",
    "fax": "fax%*PMFKA",
    "address": "address]5Ij`Z",
    "py/object": "model.contact.Contact",
    "last_name": "last_name_~z",
    "email2": "email2",
    "home_number": "home_number5|bO4 !pU",
    "nickname": "nicknameh",
    "email3": "email3(X+1Zi",
    "all_emails_from_home_page": null,
    "all_phones_from_home_page": null,
    "email": "email^>\"5im $ ",
    "homepage": "homepage|p/v !N",
    "middle_name": "middle_name#J9L]"
  },
  {
    "notes": "notesuZ",
    "first_name": "first_nameI:Pj+k2",
    "id": null,
    "company": "company c 8^ 'Y",
    "title": "titleln #",
    "byear": "byear g",
    "work_number": "work_number",
    "address_2": "address_23m0hV+",
    "phone2": "phone2XP2Z<)G\"N",
    "mobile_number": "mobile_number}jN3X)z8",
    "ayear": "ayear3/A}m Rx_",
    "fax": "fax Q",
    "address": "address ?j?Q%8",
    "py/object": "model.contact.Contact",
    "last_name": "last_name33nxeu; ;",
    "email2": "email2ZrX; sz",
    "home_number": "home_number'+P |",
    "nickname": "nickname;o)B }e=l",
    "email3": "email3 `Hpy!:#",
    "all_emails_from_home_page": null,
    "all_phones_from_home_page": null,
    "email": "emailcn",
    "homepage": "homepage@+?kWa",
    "middle_name": "middle_nameWW1\\vke"
  },
  {
    "notes": "notesGdA",
    "first_name": "first_name",
    "id": null,
    "company": "company4",
    "title": "titleAuGi\\",
    "byear": "byear(15ZHC#PZ",
    "work_number": "work_number<u%\"!% 4.",
    "address_2": "address_2",
    "phone2": "phone2< *O-j_+b",
    "mobile_number": "mobile_numberH#5 :A",
    "ayear": "ayear{",
    "fax": "faxS",
    "address": "addressC",
    "py/object": "model.contact.Contact",
    "last_name": "last_name\\k>Au",
    "email2": "email2  SF",
    "home_number": "home_number[1:4C",
    "nickname": "nickname",
    "email3": "email3\" $vu;7",
    "all_emails_from_home_page": null,
    "all_phones_from_home_page": null,
    "email": "email",
    "homepage": "homepage ",
    "middle_name": "middle_name)BW\\"
  },
  {
    "notes": "notes",
    "first_name": "first_nameRe)1",
    "id": null,
    "company": "companyCGv#?I'(",
    "title": "title",
    "byear": "byearL#%nY$",
    "work_number": "work_number5",
    "address_2": "address_2A",
    "phone2": "phone2X[?R ",
    "mobile_number": "mobile_number JXM-@t}",
    "ayear": "ayearY ",
    "fax": "fax *2=dT|",
    "address": "address%*2 n.S",
    "py/object": "model.contact.Contact",
    "last_name": "last_name?",
    "email2": "email2(2",
    "home_number": "home_numbergW",
    "nickname": "nickname",
    "email3": "email3.e9C\\;",
    "all_emails_from_home_page": null,
    "all_phones_from_home_page": null,
    "email": "email0R",
    "homepage": "homepage O\\/|/;AH",
    "middle_name": "middle_name\\STU"
  },
  {
    "notes": "notes< H   ",
    "first_name": "first_name 0 90Ht.",
    "id": null,
    "company": "companyD F 7poD3",
    "title": "title=.{? ",
    "byear": "byear (.{sp+U{",
    "work_number": "work_number*\\m%:F0l",
    "address_2": "address_27$,ha",
    "phone2": "phone2",
    "mobile_number": "mobile_number[bK",
    "ayear": "ayearp",
    "fax": "fax\\Lw34'0{",
    "address": "address",
    "py/object": "model.contact.Contact",
    "last_name": "last_name keCg*",
    "email2": "email2{ked7",
    "home_number": "home_numberbd2v\"]8.",
    "nickname": "nicknameRHI",
    "email3": "email3wJm!ZI&PQ",
    "all_emails_from_home_page": null,
    "all_phones_from_home_page": null,
    "email": "emailfI,:'a",
    "homepage": "homepage",
    "middle_name": "middle_nameBy "
  },
  {
    "notes": "notesKJ^",
    "first_name": "first_name",
    "id": null,
    "company": "companym;& i-",
    "title": "title+4W1&\"Z",
    "byear": "byear-,qr ^",
    "work_number": "work_number$Ie?3",
    "address_2": "address_27Z",
    "phone2": "phone2O wi b",
    "mobile_number": "mobile_number i|{FC_vm",
    "ayear": "ayear;,R&(?+r ",
    "fax": "faxF",
    "address": "address0`H/ \"Lp%",
    "py/object": "model.contact.Contact",
    "last_name": "last_named`{. ANf",
    "email2": "email2",
    "home_number": "home_numberU$/'gO",
    "nickname": "nickname][ fr}",
    "email3": "email3hTC[1\"",
    "all_emails_from_home_page": null,
    "all_phones_from_home_page": null,
    "email": "email/twd",
    "homepage": "homepage!:]eB9Z,",
    "middle_name": "middle_name8{ 8jh"
  },
  {
    "notes": "notes\"\\xa",
    "first_name": "first_nameap$6",
    "id": null,
    "company": "companyi~3>",
    "title": "title=|?^- 2",
    "byear": "byearZU _ O",
    "work_number": "work_numberbH[ > ",
    "address_2": "address_2 ykC",
    "phone2": "phone2U[(v+PZfc",
    "mobile_number": "mobile_numberfHEVoR ]1",
    "ayear": "ayear}",
    "fax": "faxK",
    "address": "address{d[ e%Y",
    "py/object": "model.contact.Contact",
    "last_name": "last_name",
    "email2": "email2>=5!!1 aL",
    "home_number": "home_numberS0feh",
    "nickname": "nicknameP9h3  ",
    "email3": "email3 `:hEp",
    "all_emails_from_home_page": null,
    "all_phones_from_home_page": null,
    "email": "emailR9eRGUZ",
    "homepage": "homepageuK/3Z e?",
    "middle_name": "middle_name2 2Z\"5ny"
  }
]